runcitadel/__init__.py
runcitadel/runcitadel.py
runcitadel-0.1.0.dist-info/LICENSE
runcitadel-0.1.0.dist-info/WHEEL
runcitadel-0.1.0.dist-info/METADATA
runcitadel-0.1.0.dist-info/RECORD
